odoo10_addon_web_action_conditionable-10.0.1.0.0-py2.7-nspkg.pth
odoo/addons/web_action_conditionable/README.rst
odoo/addons/web_action_conditionable/__init__.py
odoo/addons/web_action_conditionable/__manifest__.py
odoo/addons/web_action_conditionable/static/description/icon.png
odoo/addons/web_action_conditionable/static/src/js/views.js
odoo/addons/web_action_conditionable/views/view.xml
odoo10_addon_web_action_conditionable-10.0.1.0.0.dist-info/DESCRIPTION.rst
odoo10_addon_web_action_conditionable-10.0.1.0.0.dist-info/METADATA
odoo10_addon_web_action_conditionable-10.0.1.0.0.dist-info/RECORD
odoo10_addon_web_action_conditionable-10.0.1.0.0.dist-info/WHEEL
odoo10_addon_web_action_conditionable-10.0.1.0.0.dist-info/metadata.json
odoo10_addon_web_action_conditionable-10.0.1.0.0.dist-info/namespace_packages.txt
odoo10_addon_web_action_conditionable-10.0.1.0.0.dist-info/top_level.txt
